{
  "pairs": {
    "221_232": {
      "lines_roi": [
        [
          465,
          170
        ],
        [
          474,
          291
        ],
        [
          654,
          277
        ],
        [
          640,
          156
        ]
      ],
      "loftr_roi2": [
        [
          107,
          173
        ],
        [
          109,
          297
        ],
        [
          292,
          282
        ],
        [
          286,
          162
        ]
      ],
      "saved_at": "2026-04-27 22:13:01"
    }
  }
}